spdm/__init__.py
spdm/__version__.py
spdm/core/collection.py
spdm/core/directory.py
spdm/core/document.py
spdm/core/domain.py
spdm/core/entry.py
spdm/core/expression.py
spdm/core/field.py
spdm/core/file.py
spdm/core/function.py
spdm/core/functor.py
spdm/core/generic.py
spdm/core/geo_object.py
spdm/core/graph.py
spdm/core/htree.py
spdm/core/mapper.py
spdm/core/mesh.py
spdm/core/path.py
spdm/core/pluggable.py
spdm/core/query.py
spdm/core/service.py
spdm/core/signal.py
spdm/core/sp_object.py
spdm/core/sp_tree.py
spdm/core/spacetime.py
spdm/core/task.py
spdm/core/template.py
spdm/core/time.py
spdm/core/worker.py
spdm/geometry/box.py
spdm/geometry/circle.py
spdm/geometry/curve.py
spdm/geometry/line.py
spdm/geometry/plane.py
spdm/geometry/point.py
spdm/geometry/point_set.py
spdm/geometry/polygon.py
spdm/geometry/polyhedron.py
spdm/geometry/polyline.py
spdm/geometry/solid.py
spdm/geometry/surface.py
spdm/geometry/toroidal.py
spdm/geometry/transform.py
spdm/geometry/vector.py
spdm/mesh/mesh_curvilinear.py
spdm/mesh/mesh_ppoly.py
spdm/mesh/mesh_rectangular.py
spdm/mesh/mesh_rectilinear.py
spdm/mesh/mesh_structured.py
spdm/model/actor.py
spdm/model/component.py
spdm/model/context.py
spdm/model/entity.py
spdm/model/port.py
spdm/model/process.py
spdm/numlib/bvp.py
spdm/numlib/calculus.py
spdm/numlib/common.py
spdm/numlib/contours.py
spdm/numlib/interpolate.py
spdm/numlib/misc.py
spdm/numlib/numeric.py
spdm/numlib/optimize.py
spdm/numlib/picewise.py
spdm/numlib/polynomial.py
spdm/numlib/smooth.py
spdm/numlib/spline.py
spdm/plugins/data/file_h5.py
spdm/plugins/data/file_hdf5.py
spdm/plugins/data/file_json.py
spdm/plugins/data/file_mdsplus.py
spdm/plugins/data/file_namelist.py
spdm/plugins/data/file_netcdf.py
spdm/plugins/data/file_numpy.py
spdm/plugins/data/file_xml.py
spdm/plugins/data/file_yaml.py
spdm/plugins/data/service_http.py
spdm/plugins/data/service_uda.py
spdm/utils/alias.py
spdm/utils/constants.py
spdm/utils/envs.py
spdm/utils/lazy_proxy.py
spdm/utils/logger.py
spdm-0.5.2.2.dist-info/LICENSE.txt
spdm-0.5.2.2.dist-info/METADATA
spdm-0.5.2.2.dist-info/WHEEL
spdm-0.5.2.2.dist-info/top_level.txt
spdm-0.5.2.2.dist-info/RECORD
