Metadata-Version: 2.1
Name: spdm
Version: 0.5.2.2
Summary: Ontology based modeling tools.
Author-email: Zhi YU <yuzhi@ipp.ac.cn>
License: Copyright (c) 2021-present Zhi YU (Institute of Plasma Physics Chinese Academy of Sciences) 
Classifier: Development Status :: 3 - Alpha
Classifier: Intended Audience :: Science/Research
Classifier: Topic :: Scientific/Engineering :: Physics
Classifier: License :: OSI Approved :: MIT License
Classifier: Programming Language :: Python :: 3.11
Requires-Python: >=3.11
License-File: LICENSE.txt
Requires-Dist: f90nml
Requires-Dist: h5py
Requires-Dist: netcdf4
Requires-Dist: pyyaml
Requires-Dist: lxml
Requires-Dist: numpy
Requires-Dist: scipy
Requires-Dist: scikit-image
Requires-Dist: matplotlib
Requires-Dist: networkx
Requires-Dist: pygraphviz
